panosam/__init__.py
panosam/core.py
panosam/geometry.py
panosam/py.typed
panosam/api/__init__.py
panosam/api/client.py
panosam/api/models.py
panosam/dedup/__init__.py
panosam/dedup/detection.py
panosam/engines/__init__.py
panosam/engines/sam3.py
panosam/image/__init__.py
panosam/image/models.py
panosam/image/perspectives.py
panosam/sam/__init__.py
panosam/sam/engine.py
panosam/sam/models.py
panosam/sam/utils.py
panosam-0.1.1.dist-info/METADATA
panosam-0.1.1.dist-info/WHEEL
panosam-0.1.1.dist-info/licenses/LICENSE
panosam-0.1.1.dist-info/RECORD
