Metadata-Version: 2.4
Name: panosam
Version: 0.1.1
Summary: PanoSAM is a Python library for running SAM3 segmentation on equirectangular panorama images with automatic perspective projection and deduplication.
Project-URL: Homepage, https://github.com/yz3440/panosam
Project-URL: Repository, https://github.com/yz3440/panosam
Project-URL: Issues, https://github.com/yz3440/panosam/issues
Author-email: Yufeng Zhao <yufeng-zhao@outlook.com>
License: MIT
License-File: LICENSE
Keywords: 360,computer-vision,equirectangular,panorama,sam3,segmentation
Classifier: Development Status :: 3 - Alpha
Classifier: Intended Audience :: Developers
Classifier: Intended Audience :: Science/Research
Classifier: License :: OSI Approved :: MIT License
Classifier: Operating System :: OS Independent
Classifier: Programming Language :: Python :: 3
Classifier: Programming Language :: Python :: 3.11
Classifier: Programming Language :: Python :: 3.12
Classifier: Topic :: Scientific/Engineering :: Artificial Intelligence
Classifier: Topic :: Scientific/Engineering :: Image Processing
Requires-Python: >=3.11
Requires-Dist: geopandas>=0.14.0
Requires-Dist: numpy>=1.24.0
Requires-Dist: pillow>=10.0.0
Requires-Dist: py360convert>=0.1.0
Requires-Dist: shapely>=2.0.0
Requires-Dist: tqdm>=4.60.0
Provides-Extra: docs
Requires-Dist: mkdocs-terminal>=4.6.0; extra == 'docs'
Requires-Dist: mkdocs>=1.5.0; extra == 'docs'
Requires-Dist: mkdocstrings[python]>=0.24.0; extra == 'docs'
Requires-Dist: pymdown-extensions>=10.0.0; extra == 'docs'
Provides-Extra: full
Requires-Dist: accelerate>=0.25.0; extra == 'full'
Requires-Dist: matplotlib>=3.7.0; extra == 'full'
Requires-Dist: opencv-python>=4.8.0; extra == 'full'
Requires-Dist: torch>=2.0.0; extra == 'full'
Requires-Dist: torchvision>=0.15.0; extra == 'full'
Requires-Dist: transformers>=5.0.0rc1; extra == 'full'
Provides-Extra: sam3
Requires-Dist: accelerate>=0.25.0; extra == 'sam3'
Requires-Dist: opencv-python>=4.8.0; extra == 'sam3'
Requires-Dist: torch>=2.0.0; extra == 'sam3'
Requires-Dist: torchvision>=0.15.0; extra == 'sam3'
Requires-Dist: transformers>=5.0.0rc1; extra == 'sam3'
Provides-Extra: viz
Requires-Dist: matplotlib>=3.7.0; extra == 'viz'
Requires-Dist: opencv-python>=4.8.0; extra == 'viz'
